[
  [
    {
      "title": "BRYAN VON HOLST LOGO",
      "description": "",
      "image_src": "dist/images/00.png",
      "image_alt": "BRYAN"
    },
    {
      "title": "MAGICIAN CUSTOM TYPE",
      "description": "",
      "image_src": "dist/images/01.png",
      "image_alt": "MAGICIAN"
    },
    {
      "title": "SS GREAT BRITAIN LOGO",
      "description": "",
      "image_src": "dist/images/02.png",
      "image_alt": "GREAT BRITAIN"
    },
    {
      "title": "QM MONOGRAM",
      "description": "",
      "image_src": "dist/images/03.png",
      "image_alt": "MONOGRAM"
    }
  ],
  [
    {
      "title": "BRYAN VON HOLST LOGO",
      "description": "",
      "image_src": "dist/images/04.png",
      "image_alt": "BRYAN"
    },
    {
      "title": "MAGICIAN CUSTOM TYPE",
      "description": "",
      "image_src": "dist/images/05.png",
      "image_alt": "MAGICIAN"
    },
    {
      "title": "SS GREAT BRITAIN LOGO",
      "description": "",
      "image_src": "dist/images/00.png",
      "image_alt": "GREAT BRITAIN"
    },
    {
      "title": "QM MONOGRAM",
      "description": "",
      "image_src": "dist/images/01.png",
      "image_alt": "MONOGRAM"
    }
  ],
  [
    {
      "title": "BRYAN VON HOLST LOGO",
      "description": "",
      "image_src": "dist/images/00.png",
      "image_alt": "BRYAN"
    },
    {
      "title": "MAGICIAN CUSTOM TYPE",
      "description": "",
      "image_src": "dist/images/01.png",
      "image_alt": "MAGICIAN"
    },
    {
      "title": "SS GREAT BRITAIN LOGO",
      "description": "",
      "image_src": "dist/images/02.png",
      "image_alt": "GREAT BRITAIN"
    },
    {
      "title": "QM MONOGRAM",
      "description": "",
      "image_src": "dist/images/03.png",
      "image_alt": "MONOGRAM"
    }
  ]
]
